LICENSE
MANIFEST.in
README.md
requirements.txt
setup.cfg
setup.py
attributes/__init__.py
attributes/actions.py
attributes/constants.py
attributes/defaults.py
attributes/fields.py
attributes/forms.py
attributes/managers.py
attributes/querysets.py
attributes/settings.py
attributes/translation.py
attributes/utils.py
attributes/widgets.py
attributes/admin/__init__.py
attributes/admin/forms.py
attributes/locale/ru/LC_MESSAGES/django.mo
attributes/locale/ru/LC_MESSAGES/django.po
attributes/locale/uk/LC_MESSAGES/django.mo
attributes/locale/uk/LC_MESSAGES/django.po
attributes/migrations/0001_initial.py
attributes/migrations/0002_translate_field.py
attributes/migrations/__init__.py
attributes/models/__init__.py
attributes/models/attribute.py
attributes/models/attribute_option.py
attributes/models/attribute_value.py
attributes/models/service.py
attributes/static/attrs/form.js
attributes/templates/attributes-form.html
attributes/templates/change-attr-category-action.html
availability/__init__.py
availability/admin.py
availability/managers.py
availability/models.py
availability/querysets.py
availability/settings.py
availability/translation.py
availability/locale/ru/LC_MESSAGES/django.mo
availability/locale/ru/LC_MESSAGES/django.po
availability/locale/uk/LC_MESSAGES/django.mo
availability/locale/uk/LC_MESSAGES/django.po
availability/migrations/0001_initial.py
availability/migrations/__init__.py
cargo/__init__.py
cargo/admin.py
cargo/constants.py
cargo/forms.py
cargo/managers.py
cargo/model_fields.py
cargo/models.py
cargo/querysets.py
cargo/services.py
cargo/settings.py
cargo/views.py
cargo/locale/ru/LC_MESSAGES/django.mo
cargo/locale/ru/LC_MESSAGES/django.po
cargo/locale/uk/LC_MESSAGES/django.mo
cargo/locale/uk/LC_MESSAGES/django.po
cart/__init__.py
cart/config.py
cart/defaults.py
cart/forms.py
cart/models.py
cart/settings.py
cart/urls.py
cart/views.py
cart/locale/ru/LC_MESSAGES/django.mo
cart/locale/ru/LC_MESSAGES/django.po
cart/locale/uk/LC_MESSAGES/django.mo
django_mp_shop.egg-info/PKG-INFO
django_mp_shop.egg-info/SOURCES.txt
django_mp_shop.egg-info/dependency_links.txt
django_mp_shop.egg-info/requires.txt
django_mp_shop.egg-info/top_level.txt
