Metadata-Version: 2.1
Name: django-mp-shop
Version: 4.0.15
Summary: Django shop apps
Home-page: https://github.com/pmaigutyak/mp-shop
Author: Paul Maigutyak
Author-email: pmaigutyak@gmail.com
License: MIT
Download-URL: https://github.com/pmaigutyak/mp-shop/archive/4.0.15.tar.gz
Platform: UNKNOWN
License-File: LICENSE
